[
    {
        "name": "Berat"
    },
    {
        "name": "Berat"
    },
    {
        "name": "Bulqizë"
    },
    {
        "name": "Delvinë"
    },
    {
        "name": "Devoll"
    },
    {
        "name": "Dibër"
    },
    {
        "name": "Dibër"
    },
    {
        "name": "Durrës"
    },
    {
        "name": "Durrës"
    },
    {
        "name": "Elbasan"
    },
    {
        "name": "Fier"
    },
    {
        "name": "Fier"
    },
    {
        "name": "Gjirokastër"
    },
    {
        "name": "Gjirokastër"
    },
    {
        "name": "Gramsh"
    },
    {
        "name": "Has"
    },
    {
        "name": "Kavajë"
    },
    {
        "name": "Kolonjë"
    },
    {
        "name": "Korçë"
    },
    {
        "name": "Korçë"
    },
    {
        "name": "Krujë"
    },
    {
        "name": "Kuçovë"
    },
    {
        "name": "Kukës"
    },
    {
        "name": "Kukës"
    },
    {
        "name": "Kurbin"
    },
    {
        "name": "Lezhë"
    },
    {
        "name": "Lezhë"
    },
    {
        "name": "Librazhd"
    },
    {
        "name": "Lushnjë"
    },
    {
        "name": "Malësi e Madhe"
    },
    {
        "name": "Mallakastër"
    },
    {
        "name": "Mat"
    },
    {
        "name": "Mirditë"
    },
    {
        "name": "Peqin"
    },
    {
        "name": "Përmet"
    },
    {
        "name": "Pogradec"
    },
    {
        "name": "Pukë"
    },
    {
        "name": "Sarandë"
    },
    {
        "name": "Shkodër"
    },
    {
        "name": "Shkodër"
    },
    {
        "name": "Skrapar"
    },
    {
        "name": "Tepelenë"
    },
    {
        "name": "Tirana"
    },
    {
        "name": "Tirana"
    },
    {
        "name": "Tropojë"
    },
    {
        "name": "Vlorë"
    },
    {
        "name": "Vlorë"
    }
]