[
    {
        "name": "Hhohho",
        "cities": [
            "Bulembu",
            "Hhukwini",
            "Lobamba",
            "Mbabane",
            "Nkhaba",
            "Piggs Peak"
        ]
    },
    {
        "name": "Lubombo",
        "cities": [
            "Big Bend",
            "Dvokodvweni Inkhundla",
            "Lomashasha",
            "Mhlume",
            "Nsoko",
            "Siteki",
            "Tshaneni",
            "Vuvulane"
        ]
    },
    {
        "name": "Manzini",
        "cities": [
            "Bhunya",
            "Ekukhanyeni",
            "Kwaluseni",
            "Malkerns",
            "Manzini",
            "Manzini South",
            "Mhlambanyatsi",
            "Ngwempisi",
            "Ntondozi",
            "Sidvokodvo"
        ]
    },
    {
        "name": "Shiselweni",
        "cities": [
            "Hlatikulu",
            "Hluti",
            "Kubuta",
            "Lavumisa",
            "Matsanjeni",
            "Ngudzeni",
            "Nhlangano",
            "Nkwene",
            "Sigwe Inkhundla",
            "Zombodze Ikhundla"
        ]
    }
]